svector/__init__.py
svector/cli.py
svector/client.py
svector/client_new.py
svector/client_old.py
svector/conversations.py
svector/errors.py
svector/py.typed
svector_sdk-1.1.5.dist-info/licenses/LICENSE
svector_sdk-1.1.5.dist-info/METADATA
svector_sdk-1.1.5.dist-info/WHEEL
svector_sdk-1.1.5.dist-info/entry_points.txt
svector_sdk-1.1.5.dist-info/top_level.txt
svector_sdk-1.1.5.dist-info/RECORD
