Metadata-Version: 2.4
Name: svector-sdk
Version: 1.1.5
Summary: Official Python SDK for SVECTOR AI Models - Advanced conversational AI and language models
Home-page: https://github.com/svector-corporation/svector-python
Author: SVECTOR Team
Author-email: SVECTOR Team <support@svector.co.in>
Maintainer-email: SVECTOR Team <support@svector.co.in>
License: MIT
Project-URL: Homepage, https://www.svector.co.in
Project-URL: Documentation, https://platform.svector.co.in
Project-URL: Repository, https://github.com/svector-corporation/svector-python
Project-URL: Bug Tracker, https://github.com/svector-corporation/svector-python/issues
Project-URL: Changelog, https://github.com/svector-corporation/svector-python/blob/main/CHANGELOG.md
Keywords: svector,ai,machine-learning,api,llm,spec-chat,artificial-intelligence,conversational-ai,language-models
Classifier: Development Status :: 5 - Production/Stable
Classifier: Intended Audience :: Developers
Classifier: License :: OSI Approved :: MIT License
Classifier: Operating System :: OS Independent
Classifier: Programming Language :: Python :: 3
Classifier: Programming Language :: Python :: 3.8
Classifier: Programming Language :: Python :: 3.9
Classifier: Programming Language :: Python :: 3.10
Classifier: Programming Language :: Python :: 3.11
Classifier: Programming Language :: Python :: 3.12
Classifier: Topic :: Internet :: WWW/HTTP :: Dynamic Content
Classifier: Topic :: Scientific/Engineering :: Artificial Intelligence
Classifier: Topic :: Software Development :: Libraries :: Python Modules
Requires-Python: >=3.8
License-File: LICENSE
Requires-Dist: requests>=2.25.0
Requires-Dist: aiohttp>=3.8.0
Requires-Dist: typing-extensions>=4.0.0; python_version < "3.10"
Provides-Extra: dev
Requires-Dist: pytest>=6.0; extra == "dev"
Requires-Dist: pytest-cov>=2.10; extra == "dev"
Requires-Dist: black>=21.0; extra == "dev"
Requires-Dist: flake8>=3.8; extra == "dev"
Requires-Dist: mypy>=0.900; extra == "dev"
Requires-Dist: twine>=3.0; extra == "dev"
Requires-Dist: build>=0.7; extra == "dev"
Dynamic: author
Dynamic: home-page
Dynamic: license-file
Dynamic: requires-python
